hn/__init__.py
hn/client.py
hnconnector-0.1.2.dist-info/LICENSE
hnconnector-0.1.2.dist-info/METADATA
hnconnector-0.1.2.dist-info/WHEEL
hnconnector-0.1.2.dist-info/top_level.txt
hnconnector-0.1.2.dist-info/RECORD
