Metadata-Version: 2.1
Name: hnconnector
Version: 0.1.2
Summary: An unofficial Hacker News API Client Library in Python
Home-page: https://github.com/mfiro/hnconnector
Author: mfiro
Author-email: mfiro@protonmail.com
License: UNKNOWN
Platform: UNKNOWN
Classifier: Programming Language :: Python :: 3
Classifier: License :: OSI Approved :: MIT License
Classifier: Operating System :: OS Independent
License-File: LICENSE
Requires-Dist: requests
